ElGamal_c.cp310-win_amd64.pyd
ElGamal_c-2.0.2.dist-info/METADATA
ElGamal_c-2.0.2.dist-info/WHEEL
ElGamal_c-2.0.2.dist-info/top_level.txt
ElGamal_c-2.0.2.dist-info/RECORD
