Metadata-Version: 2.1
Name: ElGamal-c
Version: 2.0.2
Summary: This module is for csc281 encryption project 
Home-page: https://github.com/Wouze/csc281-project
Author: Wouze (Mohammad)
Author-email: m7mdwats1@hotmail.com
Keywords: python,c,primitive root,encryption,algamal,prime
Classifier: Development Status :: 1 - Planning
Classifier: Intended Audience :: Developers
Classifier: Programming Language :: Python :: 3
Classifier: Operating System :: Unix
Classifier: Operating System :: MacOS :: MacOS X
Classifier: Operating System :: Microsoft :: Windows
